analysis_tool/__init__.py
analysis_tool/add_multiple_candidate_label.py
analysis_tool/apply_selection.py
analysis_tool/cli.py
analysis_tool/file_merger.py
analysis_tool/track_combination_mass_calculator.py
analysis_tool/MVA/__init__.py
analysis_tool/MVA/TMVA/ConfigureEachMethod.py
analysis_tool/MVA/TMVA/__init__.py
analysis_tool/MVA/TMVA/apply_bdt_selection.py
analysis_tool/MVA/TMVA/train_tmva.py
analysis_tool/MVA/XGBoost/__init__.py
analysis_tool/MVA/XGBoost/add_xgboost_info.py
analysis_tool/MVA/XGBoost/search_optimal_hyperparameter.py
analysis_tool/MVA/XGBoost/search_optimal_hyperparameter_test.py
analysis_tool/MVA/XGBoost/train_xgboost_model.py
analysis_tool/MVA/XGBoost/xgboost_helper.py
analysis_tool/bootstrap/__init__.py
analysis_tool/bootstrap/bootstrap_sample.py
analysis_tool/constants/__init__.py
analysis_tool/constants/constants.py
analysis_tool/correlation/__init__.py
analysis_tool/correlation/check_correlation.py
analysis_tool/correlation/matrixHelper.py
analysis_tool/correlation/test/__init__.py
analysis_tool/correlation/test/test_functions.py
analysis_tool/latex/__init__.py
analysis_tool/latex/test.py
analysis_tool/latex/utils.py
analysis_tool/multiprocess/__init__.py
analysis_tool/multiprocess/poolHelper.py
analysis_tool/multiprocess/tqdm_batch.py
analysis_tool/plotter/Plot_BeforeAfter_Weights_comparison.py
analysis_tool/plotter/Plotter.py
analysis_tool/plotter/__init__.py
analysis_tool/plotter/compare_data_with_errorbar.py
analysis_tool/plotter/compare_distributions.py
analysis_tool/plotter/compare_distributions_bak_20240929.py
analysis_tool/plotter/compare_distributions_bak_20250429.py
analysis_tool/plotter/compare_distributions_classicalWay.py
analysis_tool/plotter/plot_cutflow.py
analysis_tool/plotter/plot_weighted_histogram_with_fit_and_stats.py
analysis_tool/plotter/test_debug.py
analysis_tool/plotter/utils.py
analysis_tool/reweight/__init__.py
analysis_tool/reweight/apply_weights.py
analysis_tool/reweight/reweighting.py
analysis_tool-1.0.0.dist-info/licenses/LICENSE
analysis_tool-1.0.0.dist-info/METADATA
analysis_tool-1.0.0.dist-info/WHEEL
analysis_tool-1.0.0.dist-info/entry_points.txt
analysis_tool-1.0.0.dist-info/top_level.txt
analysis_tool-1.0.0.dist-info/RECORD
