Metadata-Version: 2.4
Name: analysis-tool
Version: 1.0.0
Summary: A generic analysis tool for various data analyses. Mainly for the analysis of the LHCb experiment.
Home-page: https://github.com/JieWu-GitHub/Analysis_tools
Author: Jie Wu
Author-email: j.wu@cern.ch
License: MIT
Keywords: HEP,physics,lhcb,data-analysis,root,tmva,xgboost
Classifier: Programming Language :: Python :: 3
Classifier: Programming Language :: Python :: 3.10
Classifier: Programming Language :: Python :: 3.11
Classifier: Programming Language :: Python :: 3.12
Classifier: License :: OSI Approved :: MIT License
Classifier: Operating System :: OS Independent
Classifier: Topic :: Scientific/Engineering :: Physics
Classifier: Topic :: Scientific/Engineering :: Information Analysis
Classifier: Intended Audience :: Science/Research
Classifier: Development Status :: 4 - Beta
Requires-Python: >=3.10
License-File: LICENSE
Provides-Extra: dev
Dynamic: author
Dynamic: author-email
Dynamic: classifier
Dynamic: description
Dynamic: description-content-type
Dynamic: home-page
Dynamic: keywords
Dynamic: license
Dynamic: license-file
Dynamic: provides-extra
Dynamic: requires-python
Dynamic: summary
